{"values":[{"College Grad (%)":23.95410617247772,"District":"9"},{"College Grad (%)":38.277099475198554,"District":"8"},{"College Grad (%)":23.718020276235805,"District":"7"},{"College Grad (%)":16.804656779267425,"District":"6"},{"College Grad (%)":37.0858268865859,"District":"5"},{"College Grad (%)":54.42169347570045,"District":"4"},{"College Grad (%)":14.293255627349128,"District":"30"},{"College Grad (%)":54.528253788415235,"District":"3"},{"College Grad (%)":27.708195618643376,"District":"29"},{"College Grad (%)":36.212264047530304,"District":"28"},{"College Grad (%)":25.31728439018227,"District":"27"},{"College Grad (%)":13.845441699556597,"District":"26"},{"College Grad (%)":20.112428520660355,"District":"25"},{"College Grad (%)":11.111464411198906,"District":"24"},{"College Grad (%)":16.68189305076721,"District":"23"},{"College Grad (%)":15.685307135145186,"District":"22"},{"College Grad (%)":20.699406107744718,"District":"21"},{"College Grad (%)":22.144238804574595,"District":"20"},{"College Grad (%)":30.654024416103727,"District":"2"},{"College Grad (%)":26.461857847868448,"District":"19"},{"College Grad (%)":41.268465994234745,"District":"18"},{"College Grad (%)":42.36279873308379,"District":"17"},{"College Grad (%)":18.775564210393092,"District":"16"},{"College Grad (%)":29.90485885439098,"District":"15"},{"College Grad (%)":42.08846531361809,"District":"14"},{"College Grad (%)":43.16259883121348,"District":"13"},{"College Grad (%)":45.0821152435239,"District":"12"},{"College Grad (%)":18.85328154666936,"District":"11"},{"College Grad (%)":27.68434966211383,"District":"10"},{"College Grad (%)":26.364920111912078,"District":"1"}]}